ProFAST/__init__.py
ProFAST/examples/ProFAST_example.py
ProFAST/examples/generic_example.py
ProFAST/pyc_files/ProFAST_308.pyc
ProFAST/pyc_files/ProFAST_309.pyc
ProFAST/pyc_files/ProFAST_310.pyc
ProFAST/pyc_files/ProFAST_311.pyc
ProFAST/pyc_files/ProFAST_312.pyc
ProFAST/pyc_files/ProFAST_313.pyc
ProFAST/resources/central_biomass_gasification.json
ProFAST/resources/central_coal_gasification_w_ccs.json
ProFAST/resources/central_grid_electrolysis_PEM.json
ProFAST/resources/central_grid_electrolysis_solid_oxide.json
ProFAST/resources/central_natural_gas_reforming_no_ccs.json
ProFAST/resources/central_natural_gas_reforming_w_ccs.json
ProFAST/resources/central_solar_electrolysis.json
ProFAST/resources/central_wind_electrolysis.json
ProFAST/resources/gen_h2_fueling.json
ProFAST/resources/h2-fast-2022-07202023-generic-fueling.xlsm
ProFAST/resources/h2-fast-2022-0915.xlsm
ProFAST/resources/only_variables.json
ProFAST/resources/regional_feedstock_costs.csv
profast-1.0.6.dist-info/LICENSE
profast-1.0.6.dist-info/METADATA
profast-1.0.6.dist-info/NOTICE.txt
profast-1.0.6.dist-info/WHEEL
profast-1.0.6.dist-info/top_level.txt
profast-1.0.6.dist-info/RECORD
