Metadata-Version: 2.2
Name: ProFAST
Version: 1.0.6
Summary: Production Financial Analysis Scenario Tool
Author-email: Jamie Kee <Jamie.Kee@nrel.gov>, Michael Penev <Michael.Penev@nrel.gov>
License: END USER SOFTWARE LICENSE AGREEMENT 
Requires-Python: <3.14,>=3.8
License-File: LICENSE
License-File: NOTICE.txt
Requires-Dist: importlib_resources
Requires-Dist: matplotlib
Requires-Dist: numpy
Requires-Dist: numpy_financial
Requires-Dist: pandas
Requires-Dist: plotly
Requires-Dist: pyarrow
Requires-Dist: pytest
Requires-Dist: xlwings
